README.md
setup.py
bin/xusbboot-cli
xusbboot/__init__.py
xusbboot/bootloader.py
xusbboot/constants.py
xusbboot/crc.py
xusbboot/version.py
xusbboot.egg-info/PKG-INFO
xusbboot.egg-info/SOURCES.txt
xusbboot.egg-info/dependency_links.txt
xusbboot.egg-info/not-zip-safe
xusbboot.egg-info/requires.txt
xusbboot.egg-info/top_level.txt