Metadata-Version: 1.0
Name: xusbboot
Version: 0.0.2
Summary: Python library for xmega xusb bootloader
Home-page: http://github.com/ahtn/xusb-boot
Author: jem
Author-email: jem@seethis.link
License: MIT
Keywords: xmega,usb,hid,avr,bootloader
Platform: UNKNOWN
